stellar_keystore/__init__.py
stellar_keystore-0.1.2.dist-info/LICENSE
stellar_keystore-0.1.2.dist-info/METADATA
stellar_keystore-0.1.2.dist-info/WHEEL
stellar_keystore-0.1.2.dist-info/RECORD
