Metadata-Version: 2.1
Name: stellar-keystore
Version: 0.1.2
Summary: Tools for handling the encrypted keystore format used to store Stellar keypairs.
Home-page: https://github.com/overcat/stellar-keystore
License: Apache-2.0
Keywords: stellar,stellar.org,keystore,keyfile
Author: overcat
Author-email: 4catcode@gmail.com
Maintainer: overcat
Maintainer-email: 4catcode@gmail.com
Requires-Python: >=3.7,<4.0
Classifier: Development Status :: 4 - Beta
Classifier: Intended Audience :: Developers
Classifier: License :: OSI Approved :: Apache Software License
Classifier: Natural Language :: English
Classifier: Operating System :: OS Independent
Classifier: Programming Language :: Python
Classifier: Programming Language :: Python :: 3
Classifier: Programming Language :: Python :: 3.7
Classifier: Programming Language :: Python :: 3.8
Classifier: Programming Language :: Python :: 3.9
Classifier: Programming Language :: Python :: 3.10
Classifier: Programming Language :: Python :: 3.11
Classifier: Programming Language :: Python :: 3 :: Only
Classifier: Programming Language :: Python :: Implementation :: CPython
Classifier: Programming Language :: Python :: Implementation :: PyPy
Classifier: Topic :: Software Development :: Libraries :: Python Modules
Classifier: Typing :: Typed
Requires-Dist: PyNaCl (>=1.5.0,<2.0.0)
Requires-Dist: stellar-sdk (>=8.0.0,<9.0.0)
Project-URL: Bug Tracker, https://github.com/overcat/stellar-keystore/issues
Project-URL: Documentation, https://github.com/overcat/stellar-keystore
Project-URL: Repository, https://github.com/overcat/stellar-keystore
